[
  {
    "email": "adf",
    "name": "",
    "id": 1
  },
  {
    "email": "adadf",
    "name": "",
    "id": 2
  },
  {
    "email": "adadfss",
    "name": "",
    "id": 3
  },
  {
    "email": "adassssdfss",
    "name": "",
    "id": 4
  },
  {
    "email": "adassssdssfss",
    "name": "",
    "id": 5
  },
  {
    "email": "adassssdsdssfss",
    "name": "",
    "id": 6
  },
  {
    "email": "adassssdsdsssfss",
    "name": "Sfgssg Adfa ",
    "id": 7
  },
  {
    "email": "adassasdssdsdsssfss",
    "name": "Sfgssg Adfa ",
    "id": 8
  }
]